LICENSE
sengledwifipy/__init__.py
sengledwifipy/const.py
sengledwifipy/errors.py
sengledwifipy/helpers.py
sengledwifipy/sengledwifiapi.py
sengledwifipy/sengledwifilogin.py
sengledwifipy/sengledwifimqtt.py
sengledwifipy-0.0.9.dist-info/LICENSE
sengledwifipy-0.0.9.dist-info/METADATA
sengledwifipy-0.0.9.dist-info/WHEEL
sengledwifipy-0.0.9.dist-info/RECORD
