Metadata-Version: 2.1
Name: SengledWifiPy
Version: 0.0.9
Summary: Python package to control Sengled Wifi Devices Programmatically.
Home-page: https://github.com/cpadil/sengledwifipy
License: Apache-2.0
Keywords: Sengled,Wifi,homeassistant
Author: Cesar
Author-email: gv4plolxe@mozmail.com
Requires-Python: >=3.11,<4
Classifier: License :: OSI Approved :: Apache Software License
Classifier: Programming Language :: Python :: 3
Classifier: Programming Language :: Python :: 3.11
Classifier: Programming Language :: Python :: 3.12
Requires-Dist: aiofiles (>=23.2.1,<24.0.0)
Requires-Dist: aiohttp (>=3.9.4,<4.0.0)
Requires-Dist: backoff (>=2.2.1)
Requires-Dist: paho-mqtt (>=2.0.0,<3.0.0)
Requires-Dist: yarl
Project-URL: Repository, https://github.com/cpadil/sengledwifipy
